faostats/__init__.py
faostats/faostats.py
faostats-0.116.dist-info/LICENSE.txt
faostats-0.116.dist-info/METADATA
faostats-0.116.dist-info/WHEEL
faostats-0.116.dist-info/top_level.txt
faostats-0.116.dist-info/RECORD
